tls_request/__init__.py
tls_request/fingerprints.py
tls_request/session.py
tls_request-1.0.1.dist-info/METADATA
tls_request-1.0.1.dist-info/WHEEL
tls_request-1.0.1.dist-info/top_level.txt
tls_request-1.0.1.dist-info/RECORD
