Metadata-Version: 2.4
Name: tls_request
Version: 1.0.1
Summary: TLS fingerprinted HTTP client
Author-email: Md Josif Khan <josifkhn@gmail.com>
License: MIT
Project-URL: Homepage, https://github.com/josifkhang/tls_requests
Keywords: tls,tls client,tls_requests,tls requests,tls http client,http2
Classifier: Programming Language :: Python :: 3
Classifier: License :: OSI Approved :: MIT License
Classifier: Operating System :: OS Independent
Requires-Python: >=3.7
